MANIFEST.in
README.rst
setup.py
collective/__init__.py
collective.portaltabs.egg-info/PKG-INFO
collective.portaltabs.egg-info/SOURCES.txt
collective.portaltabs.egg-info/dependency_links.txt
collective.portaltabs.egg-info/entry_points.txt
collective.portaltabs.egg-info/namespace_packages.txt
collective.portaltabs.egg-info/not-zip-safe
collective.portaltabs.egg-info/requires.txt
collective.portaltabs.egg-info/top_level.txt
collective/portaltabs/__init__.py
collective/portaltabs/config.py
collective/portaltabs/configure.zcml
collective/portaltabs/interfaces.py
collective/portaltabs/persistent_field.py
collective/portaltabs/setuphandlers.py
collective/portaltabs/testing.py
collective/portaltabs/upgrades.zcml
collective/portaltabs/Extensions/install.py
collective/portaltabs/browser/__init__.py
collective/portaltabs/browser/configure.zcml
collective/portaltabs/browser/controlpanel.py
collective/portaltabs/browser/manage_portaltabs.pt
collective/portaltabs/browser/manage_portaltabs_view.py
collective/portaltabs/browser/newtab.png
collective/portaltabs/browser/resources/arrowBottom.png
collective/portaltabs/browser/resources/arrowDown.png
collective/portaltabs/browser/resources/arrowTop.png
collective/portaltabs/browser/resources/arrowUp.png
collective/portaltabs/browser/resources/delete_icon.png
collective/portaltabs/browser/resources/styles.css
collective/portaltabs/locales/collective.portaltabs-manual.pot
collective/portaltabs/locales/collective.portaltabs.pot
collective/portaltabs/locales/i18n.sh
collective/portaltabs/locales/it/LC_MESSAGES/collective.portaltabs.mo
collective/portaltabs/locales/it/LC_MESSAGES/collective.portaltabs.po
collective/portaltabs/profiles/default/browserlayer.xml
collective/portaltabs/profiles/default/collective.portaltabs_various.txt
collective/portaltabs/profiles/default/controlpanel.xml
collective/portaltabs/profiles/default/cssregistry.xml
collective/portaltabs/profiles/default/metadata.xml
collective/portaltabs/profiles/default/registry.xml
collective/portaltabs/profiles/default/rolemap.xml
collective/portaltabs/profiles/to_2100/rolemap.xml
collective/portaltabs/profiles/uninstall/browserlayer.xml
collective/portaltabs/profiles/uninstall/controlpanel.xml
collective/portaltabs/profiles/uninstall/cssregistry.xml
collective/portaltabs/profiles/uninstall/registry.xml
