Metadata-Version: 1.0
Name: collective.portaltabs
Version: 0.4.0
Summary: Manage site's portal tabs from Plone interface in a simple way
Home-page: http://plone.org/products/collective.portaltabs
Author: RedTurtle Technology
Author-email: sviluppoplone@redturtle.it
License: GPL
Keywords: plone portal-tabs plonegov
Platform: UNKNOWN
Classifier: Framework :: Plone
Classifier: Framework :: Plone :: 4.0
Classifier: Framework :: Plone :: 4.1
Classifier: Framework :: Plone :: 4.2
Classifier: Framework :: Plone :: 4.3
Classifier: Programming Language :: Python
Classifier: Development Status :: 5 - Production/Stable
